<annotation>
    <folder>all_img_final</folder>
    <filename>2905.jpg</filename>
    <path>/content/drive/My Drive/all_img_final/2905.jpg</path>
    <source>
        <database>Unknown</database>
    </source>
    <size>
        <width>512</width>
        <height>512</height>
        <depth>3</depth>
    </size>
    <segmented>0</segmented>
    <object>
        <name>glioma</name>
        <pose>Unspecified</pose>
        <truncated>0</truncated>
        <difficult>0</difficult>
        <bndbox>
            <xmin>253</xmin>
            <ymin>216</ymin>
            <xmax>316</xmax>
            <ymax>289</ymax>
        </bndbox>
    </object>
</annotation>
